{
    "response_code": 200,
    "total": 1,
    "debit": 1,
    "trains": [
      {
        "number": "12491",
        "name": "MOURDHWAJ EXPRESS",
        "travel_time": "21:45",
        "src_departure_time": "14:05",
        "dest_arrival_time": "11:50",
        "from_station": {
          "code": "GKP",
          "name": "GORAKHPUR"
        },
        "to_station": {
          "code": "JAT",
          "name": "JAMMU TAWI"
        },
        "classes": [
          {
            "code": "2S",
            "available": "N",
            "name": "SECOND SEATING"
          },
          {
            "code": "CC",
            "available": "N",
            "name": "AC CHAIR CAR"
          },
          {
            "code": "FC",
            "available": "N",
            "name": "FIRST CLASS"
          },
          {
            "code": "SL",
            "available": "Y",
            "name": "SLEEPER CLASS"
          },
          {
            "code": "2A",
            "available": "Y",
            "name": "SECOND AC"
          },
          {
            "code": "1A",
            "available": "Y",
            "name": "FIRST AC"
          },
          {
            "code": "3E",
            "available": "N",
            "name": "3rd AC ECONOMY"
          },
          {
            "code": "3A",
            "available": "Y",
            "name": "THIRD AC"
          }
        ],
        "days": [
          {
            "code": "MON",
            "runs": "N"
          },
          {
            "code": "TUE",
            "runs": "N"
          },
          {
            "code": "WED",
            "runs": "N"
          },
          {
            "code": "THU",
            "runs": "N"
          },
          {
            "code": "FRI",
            "runs": "N"
          },
          {
            "code": "SAT",
            "runs": "N"
          },
          {
            "code": "SUN",
            "runs": "Y"
          }
        ]
      }
    ]
  }